strictclasses/__init__.py
strictclasses/strictclass.py
strictclasses-0.1.3.dist-info/METADATA
strictclasses-0.1.3.dist-info/RECORD
strictclasses-0.1.3.dist-info/WHEEL
strictclasses-0.1.3.dist-info/top_level.txt
