Metadata-Version: 2.1
Name: strictclasses
Version: 0.1.3
Summary: A strict companion to dataclasses
Home-page: https://github.com/noamelf/strictclasses
Author: Noam Elfanbaum
Author-email: noam.elf@gmail.com
License: UNKNOWN
Platform: UNKNOWN
Requires-Dist: dataclasses
